{"appleSKU":"","appleTeamID":"","enableCodelessAutoInitialization":true,"products":[{"id":"com.cotunastudio.spaceconqueror.crystalpackone","type":0,"storeIDs":[],"defaultDescription":{"googleLocale":4,"title":"10.000 Pack","description":"Buy 10.000 crystals !"},"screenshotPath":"","applePriceTier":1,"googlePrice":{"data":[99,0,0,131072],"num":0.99},"pricingTemplateID":"","descriptions":[],"udpPrice":{"data":[0,0,0,0],"num":0.0},"payouts":[]},{"id":"com.cotunastudio.spaceconqueror.crystalpacktwo","type":0,"storeIDs":[],"defaultDescription":{"googleLocale":4,"title":"25.000 Pack","description":"Buy 25.000 crystals !"},"screenshotPath":"","applePriceTier":2,"googlePrice":{"data":[199,0,0,131072],"num":1.99},"pricingTemplateID":"","descriptions":[],"udpPrice":{"data":[0,0,0,0],"num":0.0},"payouts":[]},{"id":"com.cotunastudio.spaceconqueror.crystalpackthree","type":0,"storeIDs":[],"defaultDescription":{"googleLocale":4,"title":"38.000 Pack","description":"Buy 38.000 crystals !"},"screenshotPath":"","applePriceTier":3,"googlePrice":{"data":[299,0,0,131072],"num":2.99},"pricingTemplateID":"","descriptions":[],"udpPrice":{"data":[0,0,0,0],"num":0.0},"payouts":[]},{"id":"com.cotunastudio.spaceconqueror.freeplay","type":1,"storeIDs":[],"defaultDescription":{"googleLocale":4,"title":"Free play","description":"Respawn any wave without watching videos or paying crystals!"},"screenshotPath":"","applePriceTier":1,"googlePrice":{"data":[99,0,0,131072],"num":0.99},"pricingTemplateID":"","descriptions":[],"udpPrice":{"data":[0,0,0,0],"num":0.0},"payouts":[]}]}